xcloud/__about__.py
xcloud/__init__.py
xcloud/config.py
xcloud/benchmarks/__init__.py
xcloud/benchmarks/benchmarks.py
xcloud/cli/__init__.py
xcloud/cli/configure.py
xcloud/clients/__init__.py
xcloud/clients/cloud_links.py
xcloud/clients/deployments.py
xcloud/clients/executor_jobs.py
xcloud/clients/models_api.py
xcloud/clients/notebooks.py
xcloud/dtypes/__init__.py
xcloud/dtypes/cloud_links.py
xcloud/dtypes/deployments.py
xcloud/dtypes/executor.py
xcloud/dtypes/models_api.py
xcloud/dtypes/notebooks.py
xcloud/dtypes/shared.py
xcloud/utils/__init__.py
xcloud/utils/config_utils.py
xcloud/utils/logging.py
xcloud/utils/pydantic_to_dict.py
xcloud/utils/requests_utils.py
xcloud/utils/validations.py
xcloud/utils/zip_files.py
xcloud-0.0.19.dist-info/METADATA
xcloud-0.0.19.dist-info/WHEEL
xcloud-0.0.19.dist-info/entry_points.txt
xcloud-0.0.19.dist-info/top_level.txt
xcloud-0.0.19.dist-info/RECORD
