Metadata-Version: 2.1
Name: xcloud
Version: 0.0.19
Home-page: 
Author: Marcos Rivera Martínez, Sarthak Langde, Glenn Ko, Subhash G N, Toan Do, Roman Ageev
Author-email: marcos.rm@stochastic.ai, sarthak.langde@stochastic.ai, glenn@stochastic.ai, subhash.gn@stochastic.ai
Classifier: Programming Language :: Python :: 3
Classifier: Operating System :: OS Independent
Requires-Python: >=3.6
Requires-Dist: setuptools
Requires-Dist: pydantic <2
Requires-Dist: numpy
Requires-Dist: requests
Requires-Dist: python-dotenv
Requires-Dist: click
